setup.cfg
setup.py
genetic/__init__.py
genetic.egg-info/PKG-INFO
genetic.egg-info/SOURCES.txt
genetic.egg-info/dependency_links.txt
genetic.egg-info/requires.txt
genetic.egg-info/top_level.txt
genetic/individuals/__init__.py
genetic/individuals/_individuals.py
genetic/populations/__init__.py
genetic/populations/_populations.py
genetic/recombination/__init__.py
genetic/recombination/_recombination.py
genetic/selection/__init__.py
genetic/selection/_selection.py
genetic/util/__init__.py
genetic/util/_util.py